lunastro/__init__.py
lunastro/main.py
lunastro-0.0.22.dist-info/LICENSE
lunastro-0.0.22.dist-info/METADATA
lunastro-0.0.22.dist-info/WHEEL
lunastro-0.0.22.dist-info/top_level.txt
lunastro-0.0.22.dist-info/RECORD
