Metadata-Version: 2.1
Name: lunastro
Version: 0.0.22
Summary: python package for lunar and solar information
Home-page: https://github.com/PyndyalaCoder/lunastro
Author: Siddhu Pendyala
Author-email: elcientifico.pendyala@hotmail.com
License: MIT
Project-URL: Bug Tracker, https://github.com/PyndyalaCoder/lunastro/issues
License-File: LICENSE
Requires-Dist: requests
Requires-Dist: pytz
